django_splunk_logging
