Metadata-Version: 1.1
Name: django-splunk-logging
Version: 1.1.0
Summary: Splunk Logging integration for Django
Home-page: https://github.com/RideScout/django-splunk-logging
Author: Bo Arnold
Author-email: bo@ridescout.com
License: MIT
Keywords: splunk,logging,HTTP Event Collector
Platform: UNKNOWN
Classifier: Development Status :: 3 - Alpha
Classifier: Topic :: Software Development :: Build Tools
Classifier: License :: OSI Approved :: MIT License
Classifier: Programming Language :: Python :: 2
Classifier: Programming Language :: Python :: 2.6
Classifier: Programming Language :: Python :: 2.7
